<?xml version="1.0" encoding="UTF-8"?>
<objects serializationModel="Studio.02.01.00">
	<object class="MixerMaster" id="{d3524b81-a27f-49a3-b563-692a5c6906e1}">
		<property name="name">
			<value>Master Bus</value>
		</property>
		<relationship name="effectChain">
			<destination>{923226f3-a8f3-486e-8d53-410af2833c58}</destination>
		</relationship>
		<relationship name="panner">
			<destination>{9f155e3b-7d10-4cf2-b424-8da20ba731ed}</destination>
		</relationship>
		<relationship name="mixer">
			<destination>{5196769d-4192-454c-bde5-bdd63cb3c415}</destination>
		</relationship>
	</object>
	<object class="MixerBusEffectChain" id="{923226f3-a8f3-486e-8d53-410af2833c58}">
		<relationship name="effects">
			<destination>{d3471341-1e78-458a-8a96-de767d3429e3}</destination>
		</relationship>
	</object>
	<object class="MixerBusPanner" id="{9f155e3b-7d10-4cf2-b424-8da20ba731ed}">
		<property name="overridingOutputFormat">
			<value>2</value>
		</property>
	</object>
	<object class="MixerBusFader" id="{d3471341-1e78-458a-8a96-de767d3429e3}" />
</objects>
